aionotify/__init__.py
aionotify/aioutils.py
aionotify/base.py
aionotify/enums.py
aionotify-0.3.1.dist-info/LICENSE
aionotify-0.3.1.dist-info/METADATA
aionotify-0.3.1.dist-info/WHEEL
aionotify-0.3.1.dist-info/top_level.txt
aionotify-0.3.1.dist-info/RECORD
