Metadata-Version: 2.1
Name: aionotify
Version: 0.3.1
Summary: Asyncio-powered inotify library
Home-page: https://github.com/rbarrois/aionotify
Author: Raphaël Barrois
Author-email: raphael.barrois+aionotify@polytechnique.org
License: BSD
Keywords: asyncio,inotify
Classifier: Development Status :: 4 - Beta
Classifier: Intended Audience :: Developers
Classifier: License :: OSI Approved :: BSD License
Classifier: Topic :: Software Development :: Libraries :: Python Modules
Classifier: Operating System :: POSIX :: Linux
Classifier: Programming Language :: Python
Classifier: Programming Language :: Python :: 3.10
Classifier: Programming Language :: Python :: 3.11
Classifier: Programming Language :: Python :: 3.12
Classifier: Topic :: Software Development :: Libraries :: Python Modules
Classifier: Topic :: System :: Filesystems
Requires-Python: >=3.8
License-File: LICENSE
Provides-Extra: dev
Requires-Dist: tox; extra == "dev"
Requires-Dist: check_manifest; extra == "dev"
Requires-Dist: flake8; extra == "dev"
Requires-Dist: wheel; extra == "dev"
Requires-Dist: zest.releaser[recommended]; extra == "dev"
Requires-Dist: readme_renderer<25.0; python_version == "3.4" and extra == "dev"
Requires-Dist: colorama<=0.4.1; python_version == "3.4" and extra == "dev"
